{"colors": [{"y": 30.416068866571017, "color": "#4a4131", "name": "#4a4131"}, {"y": 15.160210425633668, "color": "#000000", "name": "#000000"}, {"y": 12.09947393591583, "color": "#312920", "name": "#312920"}, {"y": 11.095169775227163, "color": "#946a31", "name": "#946a31"}, {"y": 8.656145384983262, "color": "#6a4a29", "name": "#6a4a29"}, {"y": 6.217120994739359, "color": "#f6d59c", "name": "#f6d59c"}, {"y": 3.2998565279770444, "color": "#9c835a", "name": "#9c835a"}, {"y": 3.0607364897178386, "color": "#4a3118", "name": "#4a3118"}, {"y": 2.582496413199426, "color": "#ffc54a", "name": "#ffc54a"}, {"y": 1.8651362984218076, "color": "#bda47b", "name": "#bda47b"}, {"y": 1.4347202295552368, "color": "#9ca4a4", "name": "#9ca4a4"}, {"y": 1.3390722142515543, "color": "#fff6cd", "name": "#fff6cd"}, {"y": 1.3390722142515543, "color": "#6a6a73", "name": "#6a6a73"}, {"y": 1.099952175992348, "color": "#393941", "name": "#393941"}, {"y": 0.3347680535628886, "color": "#ac8b29", "name": "#ac8b29"}], "lightest": "rgba(255,246,205,0.45)", "pixels": [[0, 0, 0, 0, 0, 0, 0, 0, 0, 0, 0, 0, 0, 0, 0, 0, 0, 0, 0, 0, 0, 0, 0, 0, 0, 0, 0, 0, 0, 0, 0, 0, 0, 0, 0, 0, 0, 0, 0, 0, 0, 0, 0, 0, 0, 0, 0, 0, 0, 0, 0, 0, 0, 0, 0, 0, 0, 0, 0, 0, 0, 0, 0, 0, 0, 0, 0, 0, 0, 0, 0, 0, 0, 0, 0, 0, 0, 0, 0, 0, 0, 0, 0, 0, 0, 0, 0, 0, 0, 0, 0, 0, 0, 0, 0, 0], [0, 0, 0, 0, 0, 0, 0, 0, 0, 0, 0, 0, 0, 0, 0, 0, 0, 0, 0, 0, 0, 0, 0, 0, 0, 0, 0, 0, 0, 0, 0, 0, 0, 0, 0, 0, 0, 0, 0, 0, 0, 0, 0, 0, 0, 0, 0, 0, 0, 0, 0, 0, 0, 0, 0, 0, 0, 0, 0, 0, 0, 0, 0, 0, 0, 0, 0, 0, 0, 0, 0, 0, 0, 0, 0, 0, 0, 0, 0, 0, 0, 0, 0, 0, 0, 0, 0, 0, 0, 0, 0, 0, 0, 0, 0, 0], [0, 0, 0, 0, 0, 0, 0, 0, 0, 0, 0, 0, 0, 0, 0, 0, 0, 0, 0, 0, 0, 0, 0, 0, 0, 0, 0, 0, 0, 0, 0, 0, 0, 0, 0, 0, 0, 0, 0, 0, 0, 0, 0, 0, 0, 0, 0, 0, 0, 0, 0, 0, 0, 0, 0, 0, 0, 0, 0, 0, 0, 0, 0, 0, 0, 0, 0, 0, 0, 0, 0, 0, 0, 0, 0, 0, 0, 0, 0, 0, 0, 0, 0, 0, 0, 0, 0, 0, 0, 0, 0, 0, 0, 0, 0, 0], [0, 0, 0, 0, 0, 0, 0, 0, 0, 0, 0, 0, 0, 0, 0, 0, 0, 0, 0, 0, 0, 0, 0, 0, 0, 0, 0, 0, 0, 0, 0, 0, 0, 0, 0, 0, 0, 0, 0, 0, 0, 0, 0, 0, 0, 0, 0, 0, 0, 0, 0, 0, 0, 0, 0, 0, 0, 0, 0, 0, 0, 0, 0, 0, 0, 0, 0, 0, 0, 0, 0, 0, 0, 0, 0, 0, 0, 0, 0, 0, 0, 0, 0, 0, 0, 0, 0, 0, 0, 0, 0, 0, 0, 0, 0, 0], [0, 0, 0, 0, 0, 0, 0, 0, 0, 0, 0, 0, 0, 0, 0, 0, 0, 0, 0, 0, 0, 0, 0, 0, 0, 0, 0, 0, 0, 0, 0, 0, 0, 0, 0, 0, 0, 0, 0, 0, 0, 0, 0, 0, 0, 0, 0, 0, 0, 0, 0, 0, 0, 0, 0, 0, 0, 0, 0, 0, 0, 0, 0, 0, 0, 0, 0, 0, 0, 0, 0, 0, 0, 0, 0, 0, 0, 0, 0, 0, 0, 0, 0, 0, 0, 0, 0, 0, 0, 0, 0, 0, 0, 0, 0, 0], [0, 0, 0, 0, 0, 0, 0, 0, 0, 0, 0, 0, 0, 0, 0, 0, 0, 0, 0, 0, 0, 0, 0, 0, 0, 0, 0, 0, 0, 0, 0, 0, 0, 0, 0, 0, 0, 0, 0, 0, 0, 0, 0, 0, 0, 0, 0, 0, 0, 0, 0, 0, 0, 0, 0, 0, 0, 0, 0, 0, 0, 0, 0, 0, 0, 0, 0, 0, 0, 0, 0, 0, 0, 0, 0, 0, 0, 0, 0, 0, 0, 0, 0, 0, 0, 0, 0, 0, 0, 0, 0, 0, 0, 0, 0, 0], [0, 0, 0, 0, 0, 0, 0, 0, 0, 0, 0, 0, 0, 0, 0, 0, 0, 0, 0, 0, 0, 0, 0, 0, 0, 0, 0, 0, 0, 0, 0, 0, 0, 0, 0, 0, 0, 0, 0, 0, 0, 0, 0, 0, 0, 0, 0, 0, 0, 0, 0, 0, 0, 0, 0, 0, 0, 0, 0, 0, 0, 0, 0, 0, 0, 0, 0, 0, 0, 0, 0, 0, 0, 0, 0, 0, 0, 0, 0, 0, 0, 0, 0, 0, 0, 0, 0, 0, 0, 0, 0, 0, 0, 0, 0, 0], [0, 0, 0, 0, 0, 0, 0, 0, 0, 0, 0, 0, 0, 0, 0, 0, 0, 0, 0, 0, 0, 0, 0, 0, 0, 0, 0, 0, 0, 0, 0, 0, 0, 0, 0, 0, 0, 0, 0, 0, 0, 0, 0, 0, 0, 0, 0, 0, 0, 0, 0, 0, 0, 0, 0, 0, 0, 0, 0, 0, 0, 0, 0, 0, 0, 0, 0, 0, 0, 0, 0, 0, 0, 0, 0, 0, 0, 0, 0, 0, 0, 0, 0, 0, 0, 0, 0, 0, 0, 0, 0, 0, 0, 0, 0, 0], [0, 0, 0, 0, 0, 0, 0, 0, 0, 0, 0, 0, 0, 0, 0, 0, 0, 0, 0, 0, 0, 0, 0, 0, 0, 0, 0, 0, 0, 0, 0, 0, 0, 0, 0, 0, 0, 0, 0, 0, 0, 0, 0, 0, 0, 0, 0, 0, 0, 0, 0, 0, 0, 0, 0, 0, 0, 0, 0, 0, 0, 0, 0, 0, 0, 0, 0, 0, 0, 0, 0, 0, 0, 0, 0, 0, 0, 0, 0, 0, 0, 0, 0, 0, 0, 0, 0, 0, 0, 0, 0, 0, 0, 0, 0, 0], [0, 0, 0, 0, 0, 0, 0, 0, 0, 0, 0, 0, 0, 0, 0, 0, 0, 0, 0, 0, 0, 0, 0, 0, 0, 0, 0, 0, 0, 0, 0, 0, 0, 0, 0, 0, 0, 0, 0, 0, 0, 0, 0, 0, 0, 0, 0, 0, 0, 0, 0, 0, 0, 0, 0, 0, 0, 0, 0, 0, 0, 0, 0, 0, 0, 0, 0, 0, 0, 0, 0, 0, 0, 0, 0, 0, 0, 0, 0, 0, 0, 0, 0, 0, 0, 0, 0, 0, 0, 0, 0, 0, 0, 0, 0, 0], [0, 0, 0, 0, 0, 0, 0, 0, 0, 0, 0, 0, 0, 0, 0, 0, 0, 0, 0, 0, 0, 0, 0, 0, 0, 0, 0, 0, 0, 0, 0, 0, 0, 0, 0, 0, 0, 0, 0, 0, 0, 0, 0, 0, 0, 0, 0, 0, 0, 0, 0, 0, 0, 0, 0, 0, 0, 0, 0, 0, 0, 0, 0, 0, 0, 0, 0, 0, 0, 0, 0, 0, 0, 0, 0, 0, 0, 0, 0, 0, 0, 0, 0, 0, 0, 0, 0, 0, 0, 0, 0, 0, 0, 0, 0, 0], [0, 0, 0, 0, 0, 0, 0, 0, 0, 0, 0, 0, 0, 0, 0, 0, 0, 0, 0, 0, 0, 0, 0, 0, 0, 0, 0, 0, 0, 0, 0, 0, 0, 0, 0, 0, 0, 0, 0, 0, 0, 0, 0, 0, 0, 0, 0, 0, 0, 0, 0, 0, 0, 0, 0, 0, 0, 0, 0, 0, 0, 0, 0, 0, 0, 0, 0, 0, 0, 0, 0, 0, 0, 0, 0, 0, 0, 0, 0, 0, 0, 0, 0, 0, 0, 0, 0, 0, 0, 0, 0, 0, 0, 0, 0, 0], [0, 0, 0, 0, 0, 0, 0, 0, 0, 0, 0, 0, 0, 0, 0, 0, 0, 0, 0, 0, 0, 0, 0, 0, 0, 0, 0, 0, 0, 0, 0, 0, 0, 0, 0, 0, 0, 0, 0, 0, 0, 0, 0, 0, 0, 0, 0, 0, 0, 0, 0, 0, 0, 0, 0, 0, 0, 0, 0, 0, 0, 0, 0, 0, 0, 0, 0, 0, 0, 0, 0, 0, 0, 0, 0, 0, 0, 0, 0, 0, 0, 0, 0, 0, 0, 0, 0, 0, 0, 0, 0, 0, 0, 0, 0, 0], [0, 0, 0, 0, 0, 0, 0, 0, 0, 0, 0, 0, 0, 0, 0, 0, 0, 0, 0, 0, 0, 0, 0, 0, 0, 0, 0, 0, 0, 0, 0, 0, 0, 0, 0, 0, 0, 0, 0, 0, 0, 0, 0, 0, 0, 0, 0, 0, 0, 0, 0, 0, 0, 0, 0, 0, 0, 0, 0, 0, 0, 0, 0, 0, 0, 0, 0, 0, 0, 0, 0, 0, 0, 0, 0, 0, 0, 0, 0, 0, 0, 0, 0, 0, 0, 0, 0, 0, 0, 0, 0, 0, 0, 0, 0, 0], [0, 0, 0, 0, 0, 0, 0, 0, 0, 0, 0, 0, 0, 0, 0, 0, 0, 0, 0, 0, 0, 0, 0, 0, 0, 0, 0, 0, 0, 0, 0, 0, 0, 0, 0, 0, 0, 0, 0, 0, 0, 0, 0, 0, 0, 0, 0, 0, 0, 0, 0, 0, 0, 0, 0, 0, 0, 0, 0, 0, 0, 0, 0, 0, 0, 0, 0, 0, 0, 0, 0, 0, 0, 0, 0, 0, 0, 0, 0, 0, 0, 0, 0, 0, 0, 0, 0, 0, 0, 0, 0, 0, 0, 0, 0, 0], [0, 0, 0, 0, 0, 0, 0, 0, 0, 0, 0, 0, 0, 0, 0, 0, 0, 0, 0, 0, 0, 0, 0, 0, 0, 0, 0, 0, 0, 0, 0, 0, 0, 0, 0, 0, 0, 0, 0, 0, "#6a4a29", "#6a4a29", "#6a4a29", 0, 0, 0, 0, 0, 0, 0, 0, 0, 0, 0, 0, 0, 0, 0, 0, 0, 0, 0, 0, 0, 0, 0, 0, 0, 0, 0, 0, 0, 0, 0, 0, 0, 0, 0, 0, 0, 0, 0, 0, 0, 0, 0, 0, 0, 0, 0, 0, 0, 0, 0, 0, 0], [0, 0, 0, 0, 0, 0, 0, 0, 0, 0, 0, 0, 0, 0, 0, 0, 0, 0, 0, 0, 0, 0, 0, 0, 0, 0, 0, 0, 0, 0, 0, 0, 0, 0, 0, 0, 0, 0, 0, "#6a4a29", "#f6d59c", "#fff6cd", "#f6d59c", "#6a4a29", "#312920", 0, 0, 0, 0, 0, 0, 0, 0, 0, 0, 0, 0, 0, 0, 0, 0, 0, 0, 0, 0, 0, 0, 0, 0, 0, 0, 0, 0, 0, 0, 0, 0, 0, 0, 0, 0, 0, 0, 0, 0, 0, 0, 0, 0, 0, 0, 0, 0, 0, 0, 0], [0, 0, 0, 0, 0, 0, 0, 0, 0, 0, 0, 0, 0, 0, 0, 0, 0, 0, 0, 0, 0, 0, 0, 0, 0, 0, 0, 0, 0, 0, 0, 0, 0, 0, 0, 0, 0, 0, 0, 0, "#946a31", "#f6d59c", "#fff6cd", "#f6d59c", "#f6d59c", "#312920", 0, 0, 0, 0, 0, 0, 0, 0, 0, 0, 0, 0, 0, 0, 0, 0, 0, 0, 0, 0, 0, 0, 0, 0, 0, 0, 0, 0, 0, 0, 0, 0, 0, 0, 0, 0, 0, 0, 0, 0, 0, 0, 0, 0, 0, 0, 0, 0, 0, 0], [0, 0, 0, 0, 0, 0, 0, 0, 0, 0, 0, 0, 0, 0, 0, 0, 0, 0, 0, 0, 0, 0, 0, 0, 0, 0, 0, 0, 0, 0, 0, 0, 0, 0, 0, 0, 0, 0, 0, 0, 0, "#946a31", "#f6d59c", "#fff6cd", "#f6d59c", "#f6d59c", "#312920", 0, 0, 0, 0, 0, 0, 0, 0, 0, 0, 0, 0, 0, 0, 0, 0, 0, 0, 0, 0, 0, 0, 0, 0, 0, 0, 0, 0, 0, 0, 0, 0, 0, 0, 0, 0, 0, 0, 0, 0, 0, 0, 0, 0, 0, 0, 0, 0, 0], [0, 0, 0, 0, 0, 0, 0, 0, 0, 0, 0, 0, 0, 0, 0, 0, 0, 0, 0, 0, 0, 0, 0, 0, 0, 0, 0, 0, 0, 0, 0, 0, 0, 0, 0, 0, 0, 0, 0, 0, 0, "#946a31", "#f6d59c", "#fff6cd", "#f6d59c", "#f6d59c", "#312920", 0, 0, 0, 0, 0, 0, 0, 0, 0, 0, 0, 0, 0, 0, 0, 0, 0, 0, 0, 0, 0, 0, 0, 0, 0, 0, 0, 0, 0, 0, 0, 0, 0, 0, 0, 0, 0, 0, 0, 0, 0, 0, 0, 0, 0, 0, 0, 0, 0], [0, 0, 0, 0, 0, 0, 0, 0, 0, 0, 0, 0, 0, 0, 0, 0, 0, 0, 0, 0, 0, 0, 0, 0, 0, 0, 0, 0, 0, 0, 0, 0, 0, 0, 0, 0, 0, 0, 0, 0, 0, 0, "#946a31", "#f6d59c", "#fff6cd", "#f6d59c", "#f6d59c", "#312920", 0, 0, 0, 0, 0, 0, 0, 0, 0, 0, 0, 0, 0, 0, 0, 0, 0, 0, 0, 0, 0, 0, 0, 0, 0, 0, 0, 0, 0, 0, 0, 0, 0, 0, 0, 0, 0, 0, 0, 0, 0, 0, 0, 0, 0, 0, 0, 0], [0, 0, 0, 0, 0, 0, 0, 0, 0, 0, 0, 0, 0, 0, 0, 0, 0, 0, 0, 0, 0, 0, 0, 0, 0, 0, 0, 0, 0, 0, 0, 0, 0, 0, 0, 0, 0, 0, 0, 0, 0, 0, "#946a31", "#f6d59c", "#fff6cd", "#f6d59c", "#f6d59c", "#6a4a29", 0, 0, 0, 0, 0, 0, 0, 0, 0, 0, 0, 0, 0, 0, 0, 0, 0, 0, 0, 0, 0, 0, 0, 0, 0, 0, 0, 0, 0, 0, 0, 0, 0, 0, 0, 0, 0, 0, 0, 0, 0, 0, 0, 0, 0, 0, 0, 0], [0, 0, 0, 0, 0, 0, 0, 0, 0, 0, 0, 0, 0, 0, 0, 0, 0, 0, 0, 0, 0, 0, 0, 0, 0, 0, 0, 0, 0, 0, 0, 0, 0, 0, 0, 0, 0, 0, 0, 0, 0, 0, "#6a4a29", "#000000", "#000000", "#000000", "#6a4a29", "#6a4a29", 0, 0, 0, 0, 0, 0, 0, 0, 0, 0, 0, 0, 0, 0, 0, 0, 0, 0, 0, 0, 0, 0, 0, 0, 0, 0, 0, 0, 0, 0, 0, 0, 0, 0, 0, 0, 0, 0, 0, 0, 0, 0, 0, 0, 0, 0, 0, 0], [0, 0, 0, 0, 0, 0, 0, 0, 0, 0, 0, 0, 0, 0, 0, 0, 0, 0, 0, 0, 0, 0, 0, 0, 0, 0, 0, 0, 0, 0, 0, 0, 0, 0, 0, 0, 0, 0, 0, 0, 0, "#946a31", "#ffc54a", "#ffc54a", "#ffc54a", "#ffc54a", "#ffc54a", "#000000", 0, 0, 0, 0, 0, 0, 0, 0, 0, 0, 0, 0, 0, 0, 0, 0, 0, 0, 0, 0, 0, 0, 0, 0, 0, 0, 0, 0, 0, 0, 0, 0, 0, 0, 0, 0, 0, 0, 0, 0, 0, 0, 0, 0, 0, 0, 0, 0], [0, 0, 0, 0, 0, 0, 0, 0, 0, 0, 0, 0, 0, 0, 0, 0, 0, 0, 0, 0, 0, 0, 0, 0, 0, 0, 0, 0, 0, 0, 0, 0, 0, 0, 0, 0, 0, 0, 0, 0, "#946a31", "#ffc54a", "#6a4a29", "#6a4a29", "#000000", "#000000", "#ac8b29", "#ffc54a", "#000000", 0, 0, 0, 0, 0, 0, 0, 0, 0, 0, 0, 0, 0, 0, 0, 0, 0, 0, 0, 0, 0, 0, 0, 0, 0, 0, 0, 0, 0, 0, 0, 0, 0, 0, 0, 0, 0, 0, 0, 0, 0, 0, 0, 0, 0, 0, 0], [0, 0, 0, 0, 0, 0, 0, 0, 0, 0, 0, 0, 0, 0, 0, 0, 0, 0, 0, 0, 0, 0, 0, 0, 0, 0, 0, 0, 0, 0, 0, 0, 0, 0, 0, 0, 0, 0, 0, 0, "#946a31", "#6a4a29", "#f6d59c", "#fff6cd", "#f6d59c", "#f6d59c", "#6a4a29", "#ac8b29", "#000000", 0, 0, 0, 0, 0, 0, 0, 0, 0, 0, 0, 0, 0, 0, 0, 0, 0, 0, 0, 0, 0, 0, 0, 0, 0, 0, 0, 0, 0, 0, 0, 0, 0, 0, 0, 0, 0, 0, 0, 0, 0, 0, 0, 0, 0, 0, 0], [0, 0, 0, 0, 0, 0, 0, 0, 0, 0, 0, 0, 0, 0, 0, 0, 0, 0, 0, 0, 0, 0, 0, 0, 0, 0, 0, 0, 0, 0, 0, 0, 0, 0, 0, 0, 0, 0, 0, 0, 0, "#000000", "#000000", "#000000", "#000000", "#f6d59c", "#f6d59c", "#6a4a29", "#000000", 0, 0, 0, 0, 0, 0, 0, 0, 0, 0, 0, 0, 0, 0, 0, 0, 0, 0, 0, 0, 0, 0, 0, 0, 0, 0, 0, 0, 0, 0, 0, 0, 0, 0, 0, 0, 0, 0, 0, 0, 0, 0, 0, 0, 0, 0, 0], [0, 0, 0, 0, 0, 0, 0, 0, 0, 0, 0, 0, 0, 0, 0, 0, 0, 0, 0, 0, 0, 0, 0, 0, 0, 0, 0, 0, 0, 0, 0, 0, 0, 0, 0, 0, 0, 0, 0, 0, "#000000", "#ac8b29", "#ffc54a", "#ffc54a", "#ffc54a", "#6a4a29", "#000000", "#6a4a29", 0, 0, 0, 0, 0, 0, 0, 0, 0, 0, 0, 0, 0, 0, 0, 0, 0, 0, 0, 0, 0, 0, 0, 0, 0, 0, 0, 0, 0, 0, 0, 0, 0, 0, 0, 0, 0, 0, 0, 0, 0, 0, 0, 0, 0, 0, 0, 0], [0, 0, 0, 0, 0, 0, 0, 0, 0, 0, 0, 0, 0, 0, 0, 0, 0, 0, 0, 0, 0, 0, 0, 0, 0, 0, 0, 0, 0, 0, 0, 0, 0, 0, 0, 0, 0, 0, 0, "#312920", "#ffc54a", "#ffc54a", "#ffc54a", "#ffc54a", "#ffc54a", "#ffc54a", "#ffc54a", "#000000", 0, 0, 0, 0, 0, 0, 0, 0, 0, 0, 0, 0, 0, 0, 0, 0, 0, 0, 0, 0, 0, 0, 0, 0, 0, 0, 0, 0, 0, 0, 0, 0, 0, 0, 0, 0, 0, 0, 0, 0, 0, 0, 0, 0, 0, 0, 0, 0], [0, 0, 0, 0, 0, 0, 0, 0, 0, 0, 0, 0, 0, 0, 0, 0, 0, 0, 0, 0, 0, 0, 0, 0, 0, 0, 0, 0, 0, 0, 0, 0, "#312920", "#312920", "#312920", "#312920", 0, "#312920", "#000000", "#ffc54a", "#ffc54a", "#6a4a29", "#6a4a29", "#000000", "#000000", "#000000", "#ffc54a", "#ffc54a", "#000000", 0, 0, 0, 0, 0, 0, 0, 0, 0, 0, 0, 0, 0, 0, 0, 0, 0, 0, 0, 0, 0, 0, 0, 0, 0, 0, 0, 0, 0, 0, 0, 0, 0, 0, 0, 0, 0, 0, 0, 0, 0, 0, 0, 0, 0, 0, 0], [0, 0, 0, 0, 0, 0, 0, 0, 0, 0, 0, 0, 0, 0, 0, 0, 0, 0, 0, 0, 0, 0, 0, 0, 0, 0, 0, 0, 0, 0, 0, "#312920", "#4a4131", "#4a4131", "#4a4131", "#4a4131", "#312920", "#4a4131", "#000000", "#ffc54a", "#6a4a29", "#f6d59c", "#fff6cd", "#f6d59c", "#f6d59c", "#f6d59c", "#000000", "#ffc54a", "#000000", 0, 0, 0, 0, 0, 0, 0, 0, 0, 0, 0, 0, 0, 0, 0, 0, 0, 0, 0, 0, 0, 0, 0, 0, 0, 0, 0, 0, 0, 0, 0, 0, 0, 0, 0, 0, 0, 0, 0, 0, 0, 0, 0, 0, 0, 0, 0], [0, 0, 0, 0, 0, 0, 0, 0, 0, 0, 0, 0, 0, 0, 0, 0, 0, 0, 0, 0, 0, 0, 0, 0, 0, 0, 0, 0, "#312920", "#312920", "#312920", "#312920", "#4a4131", "#4a4131", "#4a4131", "#4a4131", "#312920", "#4a4131", "#4a4131", "#000000", "#f6d59c", "#f6d59c", "#fff6cd", "#f6d59c", "#f6d59c", "#f6d59c", "#f6d59c", "#000000", "#000000", "#000000", "#000000", 0, 0, 0, 0, 0, 0, 0, 0, 0, 0, 0, 0, 0, 0, 0, 0, 0, 0, 0, 0, 0, 0, 0, 0, 0, 0, 0, 0, 0, 0, 0, 0, 0, 0, 0, 0, 0, 0, 0, 0, 0, 0, 0, 0, 0], [0, 0, 0, 0, 0, 0, 0, 0, 0, 0, 0, 0, 0, 0, 0, 0, 0, 0, 0, 0, 0, 0, 0, 0, 0, 0, 0, "#312920", "#4a4131", "#4a4131", "#4a4131", "#312920", "#4a4131", "#4a4131", "#4a4131", "#4a4131", "#4a4131", "#4a4131", "#4a4131", "#000000", "#f6d59c", "#fff6cd", "#f6d59c", "#f6d59c", "#f6d59c", "#f6d59c", "#f6d59c", "#000000", "#312920", "#312920", "#312920", "#000000", 0, 0, 0, 0, 0, 0, 0, 0, 0, 0, 0, 0, 0, 0, 0, 0, 0, 0, 0, 0, 0, 0, 0, 0, 0, 0, 0, 0, 0, 0, 0, 0, 0, 0, 0, 0, 0, 0, 0, 0, 0, 0, 0, 0], [0, 0, 0, 0, 0, 0, 0, 0, 0, 0, 0, 0, 0, 0, 0, 0, 0, 0, 0, 0, 0, 0, 0, 0, 0, 0, 0, "#312920", "#4a4131", "#4a4131", "#4a4131", "#4a4131", "#4a4131", "#4a4131", "#4a4131", "#4a4131", "#4a4131", "#4a4131", "#000000", "#f6d59c", "#f6d59c", "#fff6cd", "#f6d59c", "#f6d59c", "#f6d59c", "#f6d59c", "#f6d59c", "#000000", "#312920", "#312920", "#312920", "#000000", 0, 0, 0, 0, 0, 0, 0, 0, 0, 0, 0, 0, 0, 0, 0, 0, 0, 0, 0, 0, 0, 0, 0, 0, 0, 0, 0, 0, 0, 0, 0, 0, 0, 0, 0, 0, 0, 0, 0, 0, 0, 0, 0, 0], [0, 0, 0, 0, 0, 0, 0, 0, 0, 0, 0, 0, 0, 0, 0, 0, 0, 0, 0, 0, 0, 0, 0, 0, "#312920", "#312920", "#312920", "#4a4131", "#4a4131", "#4a4131", "#4a4131", "#4a4131", "#4a4131", "#4a4131", "#4a4131", "#4a4131", "#4a4131", "#4a4131", "#000000", "#f6d59c", "#312920", "#312920", "#312920", "#f6d59c", "#f6d59c", "#f6d59c", "#000000", "#312920", "#312920", "#312920", "#000000", "#312920", "#000000", 0, 0, 0, 0, 0, 0, 0, 0, 0, 0, 0, 0, 0, 0, 0, 0, 0, 0, 0, 0, 0, 0, 0, 0, 0, 0, 0, 0, 0, 0, 0, 0, 0, 0, 0, 0, 0, 0, 0, 0, 0, 0, 0], [0, 0, 0, 0, 0, 0, 0, 0, 0, 0, 0, 0, 0, 0, 0, 0, 0, 0, 0, 0, 0, 0, 0, "#312920", "#4a4131", "#4a4131", "#312920", "#4a4131", "#4a4131", "#4a4131", "#4a4131", "#4a4131", "#4a4131", "#4a4131", "#4a4131", "#4a4131", "#4a4131", "#312920", "#312920", "#312920", "#4a4131", "#4a4131", "#4a4131", "#312920", "#000000", "#000000", "#312920", "#312920", "#312920", "#312920", "#312920", "#312920", "#000000", "#000000", 0, 0, 0, 0, 0, 0, 0, 0, 0, 0, 0, 0, 0, 0, 0, 0, 0, 0, 0, 0, 0, 0, 0, 0, 0, 0, 0, 0, 0, 0, 0, 0, 0, 0, 0, 0, 0, 0, 0, 0, 0, 0], [0, 0, 0, 0, 0, 0, 0, 0, 0, 0, 0, 0, 0, 0, 0, 0, 0, 0, 0, 0, 0, 0, "#312920", "#4a4131", "#4a4131", "#4a4131", "#4a4131", "#4a4131", "#4a4131", "#4a4131", "#4a4131", "#4a4131", "#4a4131", "#4a4131", "#4a4131", "#4a4131", "#312920", "#4a4131", "#4a4131", "#000000", "#4a4131", "#4a4131", "#4a4131", "#312920", "#4a4131", "#4a4131", "#000000", "#312920", "#312920", "#312920", "#312920", "#312920", "#312920", "#312920", "#000000", 0, 0, 0, 0, 0, 0, 0, 0, 0, 0, 0, 0, 0, 0, 0, 0, 0, 0, 0, 0, 0, 0, 0, 0, 0, 0, 0, 0, 0, 0, 0, 0, 0, 0, 0, 0, 0, 0, 0, 0, 0], [0, 0, 0, 0, 0, 0, 0, 0, 0, 0, 0, 0, 0, 0, 0, 0, 0, 0, 0, 0, 0, 0, "#312920", "#4a4131", "#4a4131", "#4a4131", "#4a4131", "#4a4131", "#4a4131", "#4a4131", "#4a4131", "#4a4131", "#4a4131", "#4a4131", "#4a4131", "#4a4131", "#312920", "#4a4131", "#4a4131", "#312920", "#4a4131", "#4a4131", "#4a4131", "#4a4131", "#4a4131", "#4a4131", "#4a4131", "#000000", "#312920", "#312920", "#000000", "#000000", "#312920", "#312920", "#000000", "#4a3118", "#4a3118", "#4a3118", "#4a3118", "#4a3118", 0, 0, 0, 0, 0, 0, 0, 0, 0, 0, 0, 0, 0, 0, 0, 0, 0, 0, 0, 0, 0, 0, 0, 0, 0, 0, 0, 0, 0, 0, 0, 0, 0, 0, 0, 0], [0, 0, 0, 0, 0, 0, 0, 0, 0, 0, 0, 0, 0, 0, 0, 0, 0, 0, 0, 0, 0, 0, "#312920", "#4a4131", "#4a4131", "#4a4131", "#4a4131", "#4a4131", "#4a4131", "#4a4131", "#4a4131", "#4a4131", "#4a4131", "#4a4131", "#4a4131", "#4a4131", "#4a4131", "#4a4131", "#4a4131", "#4a4131", "#4a4131", "#4a4131", "#4a4131", "#4a4131", "#4a4131", "#4a4131", "#4a4131", "#000000", "#312920", "#312920", "#312920", "#312920", "#000000", "#312920", "#000000", "#946a31", "#946a31", "#946a31", "#946a31", "#6a4a29", "#4a3118", "#4a3118", "#4a3118", "#6a4a29", 0, 0, 0, 0, 0, 0, 0, 0, 0, 0, 0, 0, 0, 0, 0, 0, 0, 0, 0, 0, 0, 0, 0, 0, 0, 0, 0, 0, 0, 0, 0, 0], [0, 0, 0, 0, 0, 0, 0, 0, 0, 0, 0, 0, 0, 0, 0, 0, 0, 0, 0, 0, 0, "#312920", "#312920", "#312920", "#4a4131", "#4a4131", "#4a4131", "#4a4131", "#4a4131", "#4a4131", "#4a4131", "#4a4131", "#4a4131", "#4a4131", "#4a4131", "#4a4131", "#4a4131", "#4a4131", "#4a4131", "#4a4131", "#4a4131", "#4a4131", "#4a4131", "#4a4131", "#4a4131", "#312920", "#312920", "#312920", "#312920", "#312920", "#312920", "#312920", "#312920", "#000000", "#6a4a29", "#946a31", "#946a31", "#946a31", "#6a4a29", "#6a4a29", "#6a4a29", "#6a4a29", "#4a3118", "#9c835a", "#000000", 0, 0, 0, 0, 0, 0, 0, 0, 0, 0, 0, 0, 0, 0, 0, 0, 0, 0, 0, 0, 0, 0, 0, 0, 0, 0, 0, 0, 0, 0, 0], [0, 0, 0, 0, 0, 0, 0, 0, 0, 0, 0, 0, 0, 0, 0, 0, 0, 0, 0, 0, 0, "#312920", "#4a4131", "#4a4131", "#4a4131", "#4a4131", "#4a4131", "#4a4131", "#4a4131", "#4a4131", "#4a4131", "#4a4131", "#4a4131", "#4a4131", "#4a4131", "#4a4131", "#4a4131", "#4a4131", "#4a4131", "#4a4131", "#4a4131", "#4a4131", "#4a4131", "#4a4131", "#4a4131", "#4a4131", "#312920", "#312920", "#312920", "#312920", "#312920", "#312920", "#312920", "#000000", "#000000", "#000000", "#6a4a29", "#000000", "#000000", "#6a4a29", "#6a4a29", "#4a3118", "#9c835a", "#9c835a", "#9c835a", "#000000", 0, 0, 0, 0, 0, 0, 0, 0, 0, 0, 0, 0, 0, 0, 0, 0, 0, 0, 0, 0, 0, 0, 0, 0, 0, 0, 0, 0, 0, 0], [0, 0, 0, 0, 0, 0, 0, 0, 0, 0, 0, 0, 0, 0, 0, 0, 0, 0, 0, 0, 0, "#312920", "#4a4131", "#4a4131", "#4a4131", "#4a4131", "#4a4131", "#4a4131", "#4a4131", "#4a4131", "#4a4131", "#4a4131", "#4a4131", "#4a4131", "#4a4131", "#4a4131", "#4a4131", "#4a4131", "#4a4131", "#4a4131", "#4a4131", "#4a4131", "#4a4131", "#4a4131", "#4a4131", "#4a4131", "#312920", "#312920", "#312920", "#312920", "#312920", "#312920", "#000000", "#9c835a", "#bda47b", "#9c835a", "#393941", "#9ca4a4", "#6a6a73", "#393941", "#6a4a29", "#6a4a29", "#4a3118", "#4a3118", "#9c835a", "#6a4a29", 0, 0, 0, 0, 0, 0, 0, 0, 0, 0, 0, 0, 0, 0, 0, 0, 0, 0, 0, 0, 0, 0, 0, 0, 0, 0, 0, 0, 0, 0], [0, 0, 0, 0, 0, 0, 0, 0, 0, 0, 0, 0, 0, 0, 0, 0, 0, 0, 0, 0, "#312920", "#4a4131", "#4a4131", "#4a4131", "#4a4131", "#4a4131", "#4a4131", "#4a4131", "#4a4131", "#4a4131", "#4a4131", "#4a4131", "#4a4131", "#4a4131", "#4a4131", "#4a4131", "#4a4131", "#4a4131", "#4a4131", "#4a4131", "#4a4131", "#4a4131", "#4a4131", "#4a4131", "#4a4131", "#4a4131", "#4a4131", "#4a4131", "#312920", "#312920", "#312920", "#312920", "#312920", "#000000", "#bda47b", "#bda47b", "#6a6a73", "#9ca4a4", "#9ca4a4", "#9ca4a4", "#000000", "#6a4a29", "#4a3118", "#9c835a", "#9c835a", "#9c835a", "#6a4a29", "#4a4131", "#393941", 0, 0, 0, 0, 0, 0, 0, 0, 0, 0, 0, 0, 0, 0, 0, 0, 0, 0, 0, 0, 0, 0, 0, 0, 0, 0, 0], [0, 0, 0, 0, 0, 0, 0, 0, 0, 0, 0, 0, 0, 0, 0, 0, 0, 0, 0, 0, "#312920", "#4a4131", "#4a4131", "#4a4131", "#4a4131", "#4a4131", "#4a4131", "#4a4131", "#4a4131", "#4a4131", "#4a4131", "#4a4131", "#4a4131", "#4a4131", "#4a4131", "#4a4131", "#4a4131", "#4a4131", "#4a4131", "#4a4131", "#4a4131", "#4a4131", "#4a4131", "#4a4131", "#4a4131", "#4a4131", "#4a4131", "#4a4131", "#312920", "#312920", "#312920", "#312920", "#312920", "#000000", "#bda47b", "#bda47b", "#6a6a73", "#9ca4a4", "#9ca4a4", "#9ca4a4", "#000000", "#4a3118", "#000000", "#000000", "#9c835a", "#9c835a", "#9c835a", "#6a4a29", "#6a6a73", "#000000", 0, 0, 0, 0, 0, 0, 0, 0, 0, 0, 0, 0, 0, 0, 0, 0, 0, 0, 0, 0, 0, 0, 0, 0, 0, 0], [0, 0, 0, 0, 0, 0, 0, 0, 0, 0, 0, 0, 0, 0, 0, 0, 0, 0, 0, 0, "#312920", "#4a4131", "#4a4131", "#4a4131", "#4a4131", "#4a4131", "#4a4131", "#4a4131", "#4a4131", "#4a4131", "#4a4131", "#4a4131", "#4a4131", "#4a4131", "#4a4131", "#4a4131", "#4a4131", "#4a4131", "#4a4131", "#4a4131", "#4a4131", "#4a4131", "#4a4131", "#4a4131", "#4a4131", "#4a4131", "#4a4131", "#4a4131", "#312920", "#312920", "#312920", "#312920", "#312920", "#000000", "#bda47b", "#bda47b", "#393941", "#9ca4a4", "#9ca4a4", "#6a6a73", "#000000", "#000000", 0, 0, "#000000", "#9c835a", "#9c835a", "#9c835a", "#6a6a73", "#6a6a73", "#000000", 0, 0, 0, 0, 0, 0, 0, 0, 0, 0, 0, 0, 0, 0, 0, 0, 0, 0, 0, 0, 0, 0, 0, 0, 0], [0, 0, 0, 0, 0, 0, 0, 0, 0, 0, 0, 0, 0, 0, 0, 0, 0, 0, 0, 0, 0, "#312920", "#4a4131", "#4a4131", "#4a4131", "#4a4131", "#4a4131", "#4a4131", "#4a4131", "#4a4131", "#4a4131", "#4a4131", "#4a4131", "#4a4131", "#4a4131", "#4a4131", "#4a4131", "#4a4131", "#4a4131", "#4a4131", "#4a4131", "#4a4131", "#4a4131", "#4a4131", "#4a4131", "#4a4131", "#4a4131", "#312920", "#312920", "#312920", "#000000", "#000000", "#000000", "#bda47b", "#bda47b", "#bda47b", "#393941", "#9ca4a4", "#393941", "#9ca4a4", "#000000", 0, 0, 0, "#000000", "#9c835a", "#9c835a", "#6a4a29", "#6a6a73", "#6a6a73", "#000000", 0, 0, 0, 0, 0, 0, 0, 0, 0, 0, 0, 0, 0, 0, 0, 0, 0, 0, 0, 0, 0, 0, 0, 0, 0], [0, 0, 0, 0, 0, 0, 0, 0, 0, 0, 0, 0, 0, 0, 0, 0, 0, 0, 0, 0, 0, "#312920", "#4a4131", "#4a4131", "#4a4131", "#4a4131", "#4a4131", "#4a4131", "#4a4131", "#4a4131", "#4a4131", "#4a4131", "#4a4131", "#4a4131", "#4a4131", "#4a4131", "#4a4131", "#4a4131", "#4a4131", "#4a4131", "#4a4131", "#4a4131", "#4a4131", "#4a4131", "#4a4131", "#4a4131", "#312920", "#312920", "#312920", "#312920", "#312920", "#000000", "#4a4131", "#9c835a", "#bda47b", "#bda47b", "#6a6a73", "#9ca4a4", "#9ca4a4", "#9ca4a4", "#000000", 0, 0, 0, 0, "#000000", "#393941", "#6a6a73", "#6a6a73", "#393941", "#000000", 0, 0, 0, 0, 0, 0, 0, 0, 0, 0, 0, 0, 0, 0, 0, 0, 0, 0, 0, 0, 0, 0, 0, 0, 0], [0, 0, 0, 0, 0, 0, 0, 0, 0, 0, 0, 0, 0, 0, 0, 0, 0, 0, 0, 0, "#312920", "#4a4131", "#4a4131", "#4a4131", "#4a4131", "#4a4131", "#4a4131", "#4a4131", "#4a4131", "#4a4131", "#4a4131", "#4a4131", "#4a4131", "#4a4131", "#4a4131", "#4a4131", "#4a4131", "#4a4131", "#4a4131", "#4a4131", "#4a4131", "#4a4131", "#4a4131", "#4a4131", "#4a4131", "#4a4131", "#4a4131", "#312920", "#312920", "#312920", "#000000", "#ffc54a", "#ffc54a", "#4a4131", "#bda47b", "#bda47b", "#bda47b", "#6a6a73", "#9ca4a4", "#000000", "#4a3118", "#4a3118", 0, 0, 0, 0, "#000000", "#000000", "#000000", "#000000", 0, 0, 0, 0, 0, 0, 0, 0, 0, 0, 0, 0, 0, 0, 0, 0, 0, 0, 0, 0, 0, 0, 0, 0, 0, 0], [0, 0, 0, 0, 0, 0, 0, 0, 0, 0, 0, 0, 0, 0, 0, 0, 0, 0, 0, 0, "#312920", "#4a4131", "#4a4131", "#4a4131", "#4a4131", "#4a4131", "#4a4131", "#4a4131", "#4a4131", "#4a4131", "#4a4131", "#4a4131", "#4a4131", "#4a4131", "#4a4131", "#4a4131", "#4a4131", "#4a4131", "#4a4131", "#4a4131", "#4a4131", "#4a4131", "#4a4131", "#4a4131", "#4a4131", "#4a4131", "#4a4131", "#312920", "#312920", "#000000", "#000000", "#312920", "#ffc54a", "#4a4131", "#bda47b", "#bda47b", "#bda47b", "#393941", "#000000", "#6a4a29", "#6a4a29", "#6a4a29", "#4a3118", 0, 0, 0, 0, 0, 0, 0, 0, 0, 0, 0, 0, 0, 0, 0, 0, 0, 0, 0, 0, 0, 0, 0, 0, 0, 0, 0, 0, 0, 0, 0, 0, 0], [0, 0, 0, 0, 0, 0, 0, 0, 0, 0, 0, 0, 0, 0, 0, 0, 0, 0, 0, 0, "#312920", "#4a4131", "#4a4131", "#4a4131", "#4a4131", "#4a4131", "#4a4131", "#4a4131", "#4a4131", "#4a4131", "#4a4131", "#4a4131", "#4a4131", "#4a4131", "#4a4131", "#4a4131", "#4a4131", "#4a4131", "#4a4131", "#4a4131", "#4a4131", "#4a4131", "#4a4131", "#4a4131", "#4a4131", "#4a4131", "#312920", "#000000", "#000000", "#6a4a29", "#ffc54a", "#ffc54a", "#4a4131", "#bda47b", "#bda47b", "#bda47b", "#4a4131", "#9c835a", "#000000", "#6a4a29", "#6a4a29", "#6a4a29", "#6a4a29", "#4a3118", 0, 0, 0, 0, 0, 0, 0, 0, 0, 0, 0, 0, 0, 0, 0, 0, 0, 0, 0, 0, 0, 0, 0, 0, 0, 0, 0, 0, 0, 0, 0, 0], [0, 0, 0, 0, 0, 0, 0, 0, 0, 0, 0, 0, 0, 0, 0, 0, 0, 0, 0, 0, "#312920", "#4a4131", "#4a4131", "#4a4131", "#4a4131", "#4a4131", "#4a4131", "#4a4131", "#4a4131", "#4a4131", "#4a4131", "#4a4131", "#4a4131", "#4a4131", "#4a4131", "#4a4131", "#4a4131", "#4a4131", "#4a4131", "#4a4131", "#4a4131", "#4a4131", "#4a4131", "#4a4131", "#4a4131", "#312920", "#312920", "#312920", "#312920", "#000000", "#393941", "#393941", "#4a4131", "#4a4131", "#bda47b", "#4a4131", "#9c835a", "#000000", "#6a4a29", "#6a4a29", "#6a4a29", "#4a3118", "#000000", "#000000", "#000000", 0, 0, 0, 0, 0, 0, 0, 0, 0, 0, 0, 0, 0, 0, 0, 0, 0, 0, 0, 0, 0, 0, 0, 0, 0, 0, 0, 0, 0, 0, 0], [0, 0, 0, 0, 0, 0, 0, 0, 0, 0, 0, 0, 0, 0, 0, 0, 0, 0, 0, 0, 0, "#312920", "#4a4131", "#312920", "#4a4131", "#4a4131", "#4a4131", "#4a4131", "#4a4131", "#4a4131", "#4a4131", "#4a4131", "#4a4131", "#4a4131", "#4a4131", "#4a4131", "#4a4131", "#4a4131", "#4a4131", "#4a4131", "#4a4131", "#4a4131", "#4a4131", "#4a4131", "#4a4131", "#4a4131", "#312920", "#312920", "#312920", "#312920", "#000000", "#9c835a", "#bda47b", "#4a4131", "#4a4131", "#000000", "#000000", "#6a4a29", "#6a4a29", "#6a4a29", "#6a4a29", "#6a4a29", "#4a3118", 0, 0, 0, 0, 0, 0, 0, 0, 0, 0, 0, 0, 0, 0, 0, 0, 0, 0, 0, 0, 0, 0, 0, 0, 0, 0, 0, 0, 0, 0, 0, 0, 0], [0, 0, 0, 0, 0, 0, 0, 0, 0, 0, 0, 0, 0, 0, 0, 0, 0, 0, 0, 0, 0, "#000000", "#312920", "#4a4131", "#4a4131", "#4a4131", "#4a4131", "#4a4131", "#4a4131", "#4a4131", "#4a4131", "#4a4131", "#4a4131", "#4a4131", "#4a4131", "#4a4131", "#4a4131", "#4a4131", "#4a4131", "#4a4131", "#4a4131", "#4a4131", "#4a4131", "#4a4131", "#4a4131", "#4a4131", "#312920", "#312920", "#312920", "#312920", "#000000", "#000000", "#9c835a", "#bda47b", "#000000", "#6a4a29", "#6a4a29", "#4a3118", "#4a3118", "#6a4a29", "#6a4a29", "#6a4a29", "#6a4a29", "#4a3118", 0, 0, 0, 0, 0, 0, 0, 0, 0, 0, "#6a6a73", "#393941", "#393941", 0, 0, 0, 0, 0, 0, 0, 0, 0, 0, 0, 0, 0, 0, 0, 0, 0, 0, 0], [0, 0, 0, 0, 0, 0, 0, 0, 0, 0, 0, 0, 0, 0, 0, 0, 0, 0, 0, 0, 0, 0, "#312920", "#4a4131", "#4a4131", "#4a4131", "#4a4131", "#4a4131", "#4a4131", "#4a4131", "#4a4131", "#4a4131", "#4a4131", "#4a4131", "#4a4131", "#4a4131", "#4a4131", "#4a4131", "#4a4131", "#4a4131", "#4a4131", "#4a4131", "#4a4131", "#4a4131", "#312920", "#312920", "#312920", "#312920", "#312920", "#000000", "#312920", "#312920", "#000000", "#000000", "#312920", "#000000", "#946a31", "#946a31", "#946a31", "#4a3118", "#000000", "#000000", "#6a4a29", "#000000", 0, 0, 0, 0, 0, 0, 0, 0, "#393941", "#393941", "#9ca4a4", "#9ca4a4", "#000000", 0, 0, 0, 0, 0, 0, 0, 0, 0, 0, 0, 0, 0, 0, 0, 0, 0, 0, 0], [0, 0, 0, 0, 0, 0, 0, 0, 0, 0, 0, 0, 0, 0, 0, 0, 0, 0, 0, 0, 0, "#000000", "#4a4131", "#4a4131", "#4a4131", "#4a4131", "#4a4131", "#4a4131", "#4a4131", "#4a4131", "#4a4131", "#4a4131", "#4a4131", "#4a4131", "#4a4131", "#4a4131", "#4a4131", "#312920", "#4a4131", "#4a4131", "#312920", "#4a4131", "#4a4131", "#312920", "#312920", "#312920", "#312920", "#312920", "#312920", "#312920", "#312920", "#312920", "#000000", "#312920", "#312920", "#000000", "#946a31", "#946a31", "#946a31", "#946a31", "#6a4a29", "#6a4a29", "#000000", "#000000", "#000000", "#000000", 0, 0, 0, 0, "#6a4a29", "#6a4a29", "#6a6a73", "#9ca4a4", "#9ca4a4", "#9ca4a4", "#000000", 0, 0, 0, 0, 0, 0, 0, 0, 0, 0, 0, 0, 0, 0, 0, 0, 0, 0, 0], [0, 0, 0, 0, 0, 0, 0, 0, 0, 0, 0, 0, 0, 0, 0, 0, 0, 0, 0, 0, 0, "#000000", "#4a4131", "#4a4131", "#4a4131", "#4a4131", "#4a4131", "#4a4131", "#4a4131", "#4a4131", "#4a4131", "#4a4131", "#4a4131", "#4a4131", "#4a4131", "#4a4131", "#4a4131", "#4a4131", "#000000", "#312920", "#312920", "#4a4131", "#4a4131", "#312920", "#000000", "#312920", "#312920", "#312920", "#312920", "#312920", "#312920", "#312920", "#312920", "#312920", "#312920", "#000000", "#946a31", "#946a31", "#946a31", "#946a31", "#946a31", "#6a4a29", "#6a4a29", "#6a4a29", "#6a4a29", "#000000", "#000000", "#000000", "#393941", "#6a4a29", "#9c835a", "#bda47b", "#bda47b", "#9c835a", "#9ca4a4", "#9ca4a4", "#000000", 0, 0, 0, 0, 0, 0, 0, 0, 0, 0, 0, 0, 0, 0, 0, 0, 0, 0, 0], [0, 0, 0, 0, 0, 0, 0, 0, 0, 0, 0, 0, 0, 0, 0, 0, 0, 0, 0, 0, 0, "#000000", "#4a4131", "#4a4131", "#312920", "#4a4131", "#4a4131", "#4a4131", "#4a4131", "#4a4131", "#4a4131", "#4a4131", "#4a4131", "#4a4131", "#4a4131", "#4a4131", "#4a4131", "#4a4131", "#312920", "#f6d59c", "#f6d59c", "#312920", "#000000", "#f6d59c", "#9c835a", "#000000", "#312920", "#312920", "#312920", "#312920", "#312920", "#312920", "#312920", "#312920", "#000000", "#946a31", "#946a31", "#946a31", "#946a31", "#946a31", "#946a31", "#6a4a29", "#6a4a29", "#6a4a29", "#000000", "#4a3118", "#9c835a", "#9c835a", "#9c835a", "#bda47b", "#bda47b", "#bda47b", "#bda47b", "#6a6a73", "#9ca4a4", "#9ca4a4", "#000000", 0, 0, 0, 0, 0, 0, 0, 0, 0, 0, 0, 0, 0, 0, 0, 0, 0, 0, 0], [0, 0, 0, 0, 0, 0, 0, 0, 0, 0, 0, 0, 0, 0, 0, 0, 0, 0, 0, 0, 0, 0, "#000000", "#312920", "#4a4131", "#4a4131", "#4a4131", "#4a4131", "#4a4131", "#4a4131", "#4a4131", "#4a4131", "#4a4131", "#4a4131", "#4a4131", "#4a4131", "#312920", "#312920", "#9c835a", "#f6d59c", "#fff6cd", "#f6d59c", "#f6d59c", "#f6d59c", "#f6d59c", "#f6d59c", "#000000", "#312920", "#312920", "#312920", "#312920", "#312920", "#312920", "#312920", "#312920", "#000000", "#946a31", "#946a31", "#946a31", "#946a31", "#946a31", "#946a31", "#6a4a29", "#6a4a29", "#6a4a29", "#6a4a29", "#000000", "#9c835a", "#9c835a", "#bda47b", "#bda47b", "#bda47b", "#9c835a", "#000000", "#000000", "#000000", 0, 0, 0, 0, 0, 0, 0, 0, 0, 0, 0, 0, 0, 0, 0, 0, 0, 0, 0, 0], [0, 0, 0, 0, 0, 0, 0, 0, 0, 0, 0, 0, 0, 0, 0, 0, 0, 0, 0, 0, 0, 0, 0, "#000000", "#4a4131", "#4a4131", "#4a4131", "#4a4131", "#4a4131", "#4a4131", "#4a4131", "#4a4131", "#4a4131", "#4a4131", "#4a4131", "#4a4131", "#4a4131", "#000000", "#f6d59c", "#f6d59c", "#fff6cd", "#f6d59c", "#f6d59c", "#f6d59c", "#f6d59c", "#f6d59c", "#f6d59c", "#000000", "#312920", "#312920", "#312920", "#312920", "#312920", "#312920", "#312920", "#000000", "#946a31", "#946a31", "#946a31", "#946a31", "#946a31", "#946a31", "#6a4a29", "#6a4a29", "#4a3118", "#000000", "#9c835a", "#9c835a", "#000000", "#000000", "#000000", "#000000", "#000000", 0, 0, 0, 0, 0, 0, 0, 0, 0, 0, 0, 0, 0, 0, 0, 0, 0, 0, 0, 0, 0, 0, 0], [0, 0, 0, 0, 0, 0, 0, 0, 0, 0, 0, 0, 0, 0, 0, 0, 0, 0, 0, 0, 0, 0, 0, "#000000", "#4a4131", "#4a4131", "#312920", "#4a4131", "#4a4131", "#4a4131", "#4a4131", "#4a4131", "#4a4131", "#4a4131", "#4a4131", "#4a4131", "#4a4131", "#000000", "#f6d59c", "#f6d59c", "#fff6cd", "#f6d59c", "#f6d59c", "#f6d59c", "#f6d59c", "#f6d59c", "#f6d59c", "#000000", "#312920", "#312920", "#312920", "#312920", "#000000", "#312920", "#000000", "#946a31", "#946a31", "#946a31", "#946a31", "#946a31", "#946a31", "#946a31", "#6a4a29", "#6a4a29", "#6a4a29", "#4a3118", "#000000", "#000000", 0, 0, 0, 0, 0, 0, 0, 0, 0, 0, 0, 0, 0, 0, 0, 0, 0, 0, 0, 0, 0, 0, 0, 0, 0, 0, 0, 0], [0, 0, 0, 0, 0, 0, 0, 0, 0, 0, 0, 0, 0, 0, 0, 0, 0, 0, 0, 0, 0, 0, 0, 0, "#000000", "#312920", "#4a4131", "#4a4131", "#4a4131", "#4a4131", "#4a4131", "#4a4131", "#4a4131", "#4a4131", "#4a4131", "#4a4131", "#4a4131", "#000000", "#f6d59c", "#f6d59c", "#fff6cd", "#f6d59c", "#f6d59c", "#f6d59c", "#f6d59c", "#f6d59c", "#6a4a29", "#312920", "#312920", "#312920", "#312920", "#312920", "#312920", "#000000", "#946a31", "#946a31", "#946a31", "#946a31", "#946a31", "#946a31", "#946a31", "#6a4a29", "#6a4a29", "#000000", "#000000", "#000000", 0, "#393941", "#393941", "#393941", 0, 0, 0, 0, 0, 0, 0, 0, 0, 0, 0, 0, 0, 0, 0, 0, 0, 0, 0, 0, 0, 0, 0, 0, 0, 0], [0, 0, 0, 0, 0, 0, 0, 0, 0, 0, 0, 0, 0, 0, 0, 0, 0, 0, 0, 0, 0, 0, 0, 0, "#4a3118", "#000000", "#4a4131", "#4a4131", "#4a4131", "#4a4131", "#4a4131", "#4a4131", "#4a4131", "#4a4131", "#4a4131", "#4a4131", "#4a4131", "#000000", "#9c835a", "#f6d59c", "#fff6cd", "#fff6cd", "#f6d59c", "#f6d59c", "#f6d59c", "#f6d59c", "#000000", "#312920", "#312920", "#312920", "#312920", "#312920", "#312920", "#000000", "#946a31", "#946a31", "#946a31", "#946a31", "#946a31", "#946a31", "#946a31", "#6a4a29", "#000000", 0, 0, "#393941", "#393941", "#6a6a73", "#6a6a73", "#000000", 0, 0, 0, 0, 0, 0, 0, 0, 0, 0, 0, 0, 0, 0, 0, 0, 0, 0, 0, 0, 0, 0, 0, 0, 0, 0], [0, 0, 0, 0, 0, 0, 0, 0, 0, 0, 0, 0, 0, 0, 0, 0, 0, 0, 0, 0, 0, 0, 0, 0, "#4a3118", "#946a31", "#000000", "#000000", "#312920", "#312920", "#4a4131", "#4a4131", "#4a4131", "#4a4131", "#4a4131", "#4a4131", "#4a4131", "#4a4131", "#000000", "#f6d59c", "#f6d59c", "#fff6cd", "#f6d59c", "#f6d59c", "#f6d59c", "#9c835a", "#000000", "#312920", "#312920", "#000000", "#312920", "#312920", "#000000", "#946a31", "#946a31", "#946a31", "#946a31", "#946a31", "#6a4a29", "#000000", "#000000", "#000000", 0, 0, "#6a4a29", "#9c835a", "#6a6a73", "#6a6a73", "#6a6a73", "#000000", 0, 0, 0, 0, 0, 0, 0, 0, 0, 0, 0, 0, 0, 0, 0, 0, 0, 0, 0, 0, 0, 0, 0, 0, 0, 0], [0, 0, 0, 0, 0, 0, 0, 0, 0, 0, 0, 0, 0, 0, 0, 0, 0, 0, 0, 0, 0, 0, 0, 0, "#4a3118", "#946a31", "#946a31", "#946a31", "#946a31", "#000000", "#4a4131", "#4a4131", "#4a4131", "#4a4131", "#4a4131", "#4a4131", "#4a4131", "#4a4131", "#000000", "#f6d59c", "#6a4a29", "#000000", "#000000", "#000000", "#000000", "#9c835a", "#000000", "#312920", "#312920", "#312920", "#000000", "#000000", "#946a31", "#946a31", "#946a31", "#4a3118", "#4a3118", "#000000", "#000000", "#6a4a29", "#000000", "#6a4a29", "#6a4a29", "#6a4a29", "#9c835a", "#9c835a", "#393941", "#6a6a73", "#6a6a73", "#000000", 0, 0, 0, 0, 0, 0, 0, 0, 0, 0, 0, 0, 0, 0, 0, 0, 0, 0, 0, 0, 0, 0, 0, 0, 0, 0], [0, 0, 0, 0, 0, 0, 0, 0, 0, 0, 0, 0, 0, 0, 0, 0, 0, 0, 0, 0, 0, 0, 0, 0, "#4a3118", "#946a31", "#946a31", "#946a31", "#946a31", "#946a31", "#000000", "#4a4131", "#4a4131", "#312920", "#4a4131", "#312920", "#4a4131", "#4a4131", "#000000", "#6a4a29", "#ffc54a", "#ffc54a", "#ffc54a", "#ffc54a", "#ac8b29", "#000000", "#6a4a29", "#312920", "#312920", "#312920", "#000000", "#946a31", "#946a31", "#6a4a29", "#4a3118", "#6a4a29", "#6a4a29", "#6a4a29", "#6a4a29", "#6a4a29", "#000000", "#9c835a", "#9c835a", "#9c835a", "#9c835a", "#9c835a", "#393941", "#000000", "#000000", 0, 0, 0, 0, 0, 0, 0, 0, 0, 0, 0, 0, 0, 0, 0, 0, 0, 0, 0, 0, 0, 0, 0, 0, 0, 0, 0], [0, 0, 0, 0, 0, 0, 0, 0, 0, 0, 0, 0, 0, 0, 0, 0, 0, 0, 0, 0, 0, 0, 0, 0, 0, "#4a3118", "#946a31", "#946a31", "#946a31", "#946a31", "#946a31", "#000000", "#000000", "#312920", "#000000", "#4a4131", "#4a4131", "#4a4131", "#000000", "#ffc54a", "#ffc54a", "#ffc54a", "#ffc54a", "#ffc54a", "#ffc54a", "#ffc54a", "#000000", "#312920", "#000000", "#000000", "#946a31", "#946a31", "#946a31", "#946a31", "#946a31", "#6a4a29", "#6a4a29", "#6a4a29", "#6a4a29", "#000000", "#6a4a29", "#4a3118", "#9c835a", "#9c835a", "#000000", "#000000", 0, 0, 0, 0, 0, 0, 0, 0, 0, 0, 0, 0, 0, 0, 0, 0, 0, 0, 0, 0, 0, 0, 0, 0, 0, 0, 0, 0, 0, 0], [0, 0, 0, 0, 0, 0, 0, 0, 0, 0, 0, 0, 0, 0, 0, 0, 0, 0, 0, 0, 0, 0, 0, 0, 0, "#4a3118", "#946a31", "#946a31", "#946a31", "#946a31", "#946a31", "#946a31", "#946a31", "#946a31", "#946a31", "#000000", "#312920", "#4a3118", "#ffc54a", "#ffc54a", "#6a4a29", "#000000", "#000000", "#000000", "#000000", "#ffc54a", "#ffc54a", "#000000", "#946a31", "#946a31", "#946a31", "#946a31", "#946a31", "#946a31", "#6a4a29", "#6a4a29", "#6a4a29", "#6a4a29", "#6a4a29", "#000000", "#4a3118", "#9c835a", "#9c835a", "#000000", 0, 0, 0, 0, 0, 0, 0, 0, 0, 0, 0, 0, 0, 0, 0, 0, 0, 0, 0, 0, 0, 0, 0, 0, 0, 0, 0, 0, 0, 0, 0, 0], [0, 0, 0, 0, 0, 0, 0, 0, 0, 0, 0, 0, 0, 0, 0, 0, 0, 0, 0, 0, 0, 0, 0, 0, 0, 0, "#4a3118", "#4a3118", "#946a31", "#946a31", "#946a31", "#946a31", "#946a31", "#946a31", "#946a31", "#946a31", "#946a31", "#000000", "#ffc54a", "#6a4a29", "#f6d59c", "#fff6cd", "#f6d59c", "#f6d59c", "#9c835a", "#000000", "#ffc54a", "#000000", "#946a31", "#946a31", "#946a31", "#946a31", "#946a31", "#6a4a29", "#6a4a29", "#6a4a29", "#6a4a29", "#6a4a29", "#000000", "#6a4a29", "#6a4a29", "#000000", "#000000", 0, 0, 0, 0, 0, 0, 0, 0, 0, 0, 0, 0, 0, 0, 0, 0, 0, 0, 0, 0, 0, 0, 0, 0, 0, 0, 0, 0, 0, 0, 0, 0, 0], [0, 0, 0, 0, 0, 0, 0, 0, 0, 0, 0, 0, 0, 0, 0, 0, 0, 0, 0, 0, 0, 0, 0, 0, 0, 0, 0, 0, "#000000", "#000000", "#946a31", "#946a31", "#946a31", "#946a31", "#946a31", "#946a31", "#946a31", "#000000", "#ac8b29", "#f6d59c", "#f6d59c", "#fff6cd", "#f6d59c", "#f6d59c", "#f6d59c", "#6a4a29", "#ac8b29", "#000000", "#946a31", "#6a4a29", "#6a4a29", "#6a4a29", "#4a3118", "#6a4a29", "#6a4a29", "#6a4a29", "#4a3118", "#6a4a29", "#000000", "#4a3118", "#4a3118", 0, 0, 0, 0, 0, 0, 0, 0, 0, 0, 0, 0, 0, 0, 0, 0, 0, 0, 0, 0, 0, 0, 0, 0, 0, 0, 0, 0, 0, 0, 0, 0, 0, 0, 0], [0, 0, 0, 0, 0, 0, 0, 0, 0, 0, 0, 0, 0, 0, 0, 0, 0, 0, 0, 0, 0, 0, 0, 0, 0, 0, 0, 0, 0, 0, "#000000", "#000000", "#946a31", "#946a31", "#946a31", "#946a31", "#946a31", "#946a31", "#000000", "#f6d59c", "#9c835a", "#6a4a29", "#6a4a29", "#6a4a29", "#9c835a", "#f6d59c", "#000000", "#946a31", "#946a31", "#946a31", "#946a31", "#946a31", "#946a31", "#4a3118", "#000000", "#6a4a29", "#6a4a29", "#000000", "#000000", 0, 0, 0, 0, 0, 0, 0, 0, 0, 0, 0, 0, 0, 0, 0, 0, 0, 0, 0, 0, 0, 0, 0, 0, 0, 0, 0, 0, 0, 0, 0, 0, 0, 0, 0, 0, 0], [0, 0, 0, 0, 0, 0, 0, 0, 0, 0, 0, 0, 0, 0, 0, 0, 0, 0, 0, 0, 0, 0, 0, 0, 0, 0, 0, 0, 0, 0, 0, 0, "#000000", "#946a31", "#946a31", "#946a31", "#946a31", "#946a31", "#946a31", "#000000", "#ffc54a", "#ffc54a", "#ffc54a", "#ffc54a", "#ffc54a", "#6a4a29", "#000000", "#946a31", "#946a31", "#946a31", "#946a31", "#946a31", "#946a31", "#946a31", "#6a4a29", "#000000", "#000000", 0, 0, 0, 0, 0, 0, 0, 0, 0, 0, 0, 0, 0, 0, 0, 0, 0, 0, 0, 0, 0, 0, 0, 0, 0, 0, 0, 0, 0, 0, 0, 0, 0, 0, 0, 0, 0, 0, 0], [0, 0, 0, 0, 0, 0, 0, 0, 0, 0, 0, 0, 0, 0, 0, 0, 0, 0, 0, 0, 0, 0, 0, 0, 0, 0, 0, 0, 0, 0, 0, 0, 0, "#000000", "#946a31", "#946a31", "#946a31", "#946a31", "#000000", "#ffc54a", "#ffc54a", "#000000", "#000000", "#000000", "#6a4a29", "#ffc54a", "#6a4a29", "#946a31", "#946a31", "#946a31", "#946a31", "#946a31", "#946a31", "#946a31", "#6a4a29", "#6a4a29", "#000000", 0, 0, 0, 0, 0, 0, 0, 0, 0, 0, 0, 0, 0, 0, 0, 0, 0, 0, 0, 0, 0, 0, 0, 0, 0, 0, 0, 0, 0, 0, 0, 0, 0, 0, 0, 0, 0, 0, 0], [0, 0, 0, 0, 0, 0, 0, 0, 0, 0, 0, 0, 0, 0, 0, 0, 0, 0, 0, 0, 0, 0, 0, 0, 0, 0, 0, 0, 0, 0, 0, 0, 0, 0, "#000000", "#946a31", "#946a31", "#946a31", "#000000", "#ffc54a", "#6a4a29", "#f6d59c", "#fff6cd", "#f6d59c", "#6a4a29", "#ac8b29", "#000000", "#946a31", "#946a31", "#946a31", "#946a31", "#946a31", "#946a31", "#946a31", "#6a4a29", "#6a4a29", "#6a4a29", "#000000", 0, 0, 0, 0, 0, 0, 0, 0, 0, 0, 0, "#000000", "#000000", 0, 0, 0, 0, 0, 0, 0, 0, 0, 0, 0, 0, 0, 0, 0, 0, 0, 0, 0, 0, 0, 0, 0, 0, 0], [0, 0, 0, 0, 0, 0, 0, 0, 0, 0, 0, 0, 0, 0, 0, 0, 0, 0, 0, 0, 0, 0, 0, 0, 0, 0, 0, 0, 0, 0, 0, 0, 0, 0, "#4a3118", "#4a3118", "#946a31", "#946a31", "#000000", "#6a4a29", "#f6d59c", "#f6d59c", "#fff6cd", "#f6d59c", "#f6d59c", "#000000", "#000000", "#946a31", "#946a31", "#946a31", "#946a31", "#946a31", "#946a31", "#946a31", "#6a4a29", "#6a4a29", "#6a4a29", "#6a4a29", "#000000", "#000000", 0, 0, 0, 0, 0, 0, 0, "#6a4a29", "#000000", "#9ca4a4", "#9ca4a4", "#000000", 0, 0, 0, 0, 0, 0, 0, 0, 0, 0, 0, 0, 0, 0, 0, 0, 0, 0, 0, 0, 0, 0, 0, 0], [0, 0, 0, 0, 0, 0, 0, 0, 0, 0, 0, 0, 0, 0, 0, 0, 0, 0, 0, 0, 0, 0, 0, 0, 0, 0, 0, 0, 0, 0, 0, 0, 0, 0, "#4a3118", "#946a31", "#6a4a29", "#946a31", "#946a31", "#000000", "#f6d59c", "#f6d59c", "#fff6cd", "#f6d59c", "#f6d59c", "#000000", "#946a31", "#946a31", "#946a31", "#946a31", "#946a31", "#946a31", "#946a31", "#6a4a29", "#6a4a29", "#6a4a29", "#6a4a29", "#6a4a29", "#6a4a29", "#6a4a29", "#4a3118", "#000000", 0, 0, 0, "#6a4a29", "#6a4a29", "#9c835a", "#9ca4a4", "#9ca4a4", "#9ca4a4", "#000000", 0, 0, 0, 0, 0, 0, 0, 0, 0, 0, 0, 0, 0, 0, 0, 0, 0, 0, 0, 0, 0, 0, 0, 0], [0, 0, 0, 0, 0, 0, 0, 0, 0, 0, 0, 0, 0, 0, 0, 0, 0, 0, 0, 0, 0, 0, 0, 0, 0, 0, 0, 0, 0, 0, 0, 0, "#4a3118", "#4a3118", "#946a31", "#946a31", "#946a31", "#946a31", "#946a31", "#000000", "#f6d59c", "#fff6cd", "#f6d59c", "#f6d59c", "#9c835a", "#000000", "#946a31", "#946a31", "#946a31", "#946a31", "#946a31", "#946a31", "#946a31", "#6a4a29", "#6a4a29", "#6a4a29", "#6a4a29", "#6a4a29", "#6a4a29", "#6a4a29", "#4a3118", "#9c835a", "#4a3118", "#000000", "#000000", "#bda47b", "#bda47b", "#bda47b", "#6a6a73", "#9ca4a4", "#6a6a73", "#000000", 0, 0, 0, 0, 0, 0, 0, 0, 0, 0, 0, 0, 0, 0, 0, 0, 0, 0, 0, 0, 0, 0, 0, 0], [0, 0, 0, 0, 0, 0, 0, 0, 0, 0, 0, 0, 0, 0, 0, 0, 0, 0, 0, 0, 0, 0, 0, 0, 0, 0, 0, 0, 0, 0, 0, "#000000", "#946a31", "#946a31", "#946a31", "#6a4a29", "#4a3118", "#946a31", "#946a31", "#4a3118", "#f6d59c", "#fff6cd", "#f6d59c", "#f6d59c", "#000000", "#946a31", "#946a31", "#946a31", "#946a31", "#946a31", "#946a31", "#946a31", "#6a4a29", "#6a4a29", "#6a4a29", "#6a4a29", "#6a4a29", "#6a4a29", "#6a4a29", "#6a4a29", "#4a3118", "#4a3118", "#9c835a", "#9c835a", "#9c835a", "#bda47b", "#bda47b", "#9c835a", "#6a6a73", "#6a6a73", "#6a6a73", "#000000", 0, 0, 0, 0, 0, 0, 0, 0, 0, 0, 0, 0, 0, 0, 0, 0, 0, 0, 0, 0, 0, 0, 0, 0], [0, 0, 0, 0, 0, 0, 0, 0, 0, 0, 0, 0, 0, 0, 0, 0, 0, 0, 0, 0, 0, 0, 0, 0, 0, 0, 0, 0, 0, 0, 0, 0, "#000000", "#000000", "#4a3118", "#4a3118", "#946a31", "#946a31", "#000000", "#f6d59c", "#fff6cd", "#f6d59c", "#f6d59c", "#9c835a", "#000000", "#946a31", "#946a31", "#946a31", "#946a31", "#946a31", "#946a31", "#6a4a29", "#6a4a29", "#6a4a29", "#000000", "#000000", "#000000", "#000000", "#6a4a29", "#4a3118", "#9c835a", "#9c835a", "#9c835a", "#9c835a", "#9c835a", "#9c835a", "#bda47b", "#000000", "#000000", "#000000", "#000000", 0, 0, 0, 0, 0, 0, 0, 0, 0, 0, 0, 0, 0, 0, 0, 0, 0, 0, 0, 0, 0, 0, 0, 0, 0], [0, 0, 0, 0, 0, 0, 0, 0, 0, 0, 0, 0, 0, 0, 0, 0, 0, 0, 0, 0, 0, 0, 0, 0, 0, 0, 0, 0, 0, 0, 0, 0, 0, 0, 0, "#4a3118", "#4a3118", "#4a3118", "#000000", "#f6d59c", "#fff6cd", "#f6d59c", "#f6d59c", "#000000", "#312920", "#000000", "#000000", "#946a31", "#946a31", "#6a4a29", "#6a4a29", "#000000", "#000000", "#000000", 0, 0, 0, 0, "#000000", "#6a4a29", "#000000", "#000000", "#9c835a", "#9c835a", "#000000", "#000000", "#000000", 0, 0, 0, 0, 0, 0, 0, 0, 0, 0, 0, 0, 0, 0, 0, 0, 0, 0, 0, 0, 0, 0, 0, 0, 0, 0, 0, 0, 0], [0, 0, 0, 0, 0, 0, 0, 0, 0, 0, 0, 0, 0, 0, 0, 0, 0, 0, 0, 0, 0, 0, 0, 0, 0, 0, 0, 0, 0, 0, 0, 0, 0, 0, 0, 0, 0, "#000000", "#f6d59c", "#fff6cd", "#f6d59c", "#f6d59c", "#000000", 0, 0, 0, 0, "#000000", "#000000", "#000000", "#000000", 0, 0, 0, 0, 0, 0, 0, 0, "#000000", 0, 0, "#000000", "#000000", 0, 0, 0, 0, 0, 0, 0, 0, 0, 0, 0, 0, 0, 0, 0, 0, 0, 0, 0, 0, 0, 0, 0, 0, 0, 0, 0, 0, 0, 0, 0, 0], [0, 0, 0, 0, 0, 0, 0, 0, 0, 0, 0, 0, 0, 0, 0, 0, 0, 0, 0, 0, 0, 0, 0, 0, 0, 0, 0, 0, 0, 0, 0, 0, 0, 0, 0, 0, "#000000", "#f6d59c", "#f6d59c", "#f6d59c", "#000000", "#000000", 0, 0, 0, 0, 0, 0, 0, 0, 0, 0, 0, 0, 0, 0, 0, 0, 0, 0, 0, 0, 0, 0, 0, 0, 0, 0, 0, 0, 0, 0, 0, 0, 0, 0, 0, 0, 0, 0, 0, 0, 0, 0, 0, 0, 0, 0, 0, 0, 0, 0, 0, 0, 0, 0], [0, 0, 0, 0, 0, 0, 0, 0, 0, 0, 0, 0, 0, 0, 0, 0, 0, 0, 0, 0, 0, 0, 0, 0, 0, 0, 0, 0, 0, 0, 0, 0, 0, 0, 0, 0, "#000000", "#000000", "#000000", "#000000", 0, 0, 0, 0, 0, 0, 0, 0, 0, 0, 0, 0, 0, 0, 0, 0, 0, 0, 0, 0, 0, 0, 0, 0, 0, 0, 0, 0, 0, 0, 0, 0, 0, 0, 0, 0, 0, 0, 0, 0, 0, 0, 0, 0, 0, 0, 0, 0, 0, 0, 0, 0, 0, 0, 0, 0], [0, 0, 0, 0, 0, 0, 0, 0, 0, 0, 0, 0, 0, 0, 0, 0, 0, 0, 0, 0, 0, 0, 0, 0, 0, 0, 0, 0, 0, 0, 0, 0, 0, 0, 0, 0, 0, 0, 0, 0, 0, 0, 0, 0, 0, 0, 0, 0, 0, 0, 0, 0, 0, 0, 0, 0, 0, 0, 0, 0, 0, 0, 0, 0, 0, 0, 0, 0, 0, 0, 0, 0, 0, 0, 0, 0, 0, 0, 0, 0, 0, 0, 0, 0, 0, 0, 0, 0, 0, 0, 0, 0, 0, 0, 0, 0], [0, 0, 0, 0, 0, 0, 0, 0, 0, 0, 0, 0, 0, 0, 0, 0, 0, 0, 0, 0, 0, 0, 0, 0, 0, 0, 0, 0, 0, 0, 0, 0, 0, 0, 0, 0, 0, 0, 0, 0, 0, 0, 0, 0, 0, 0, 0, 0, 0, 0, 0, 0, 0, 0, 0, 0, 0, 0, 0, 0, 0, 0, 0, 0, 0, 0, 0, 0, 0, 0, 0, 0, 0, 0, 0, 0, 0, 0, 0, 0, 0, 0, 0, 0, 0, 0, 0, 0, 0, 0, 0, 0, 0, 0, 0, 0], [0, 0, 0, 0, 0, 0, 0, 0, 0, 0, 0, 0, 0, 0, 0, 0, 0, 0, 0, 0, 0, 0, 0, 0, 0, 0, 0, 0, 0, 0, 0, 0, 0, 0, 0, 0, 0, 0, 0, 0, 0, 0, 0, 0, 0, 0, 0, 0, 0, 0, 0, 0, 0, 0, 0, 0, 0, 0, 0, 0, 0, 0, 0, 0, 0, 0, 0, 0, 0, 0, 0, 0, 0, 0, 0, 0, 0, 0, 0, 0, 0, 0, 0, 0, 0, 0, 0, 0, 0, 0, 0, 0, 0, 0, 0, 0], [0, 0, 0, 0, 0, 0, 0, 0, 0, 0, 0, 0, 0, 0, 0, 0, 0, 0, 0, 0, 0, 0, 0, 0, 0, 0, 0, 0, 0, 0, 0, 0, 0, 0, 0, 0, 0, 0, 0, 0, 0, 0, 0, 0, 0, 0, 0, 0, 0, 0, 0, 0, 0, 0, 0, 0, 0, 0, 0, 0, 0, 0, 0, 0, 0, 0, 0, 0, 0, 0, 0, 0, 0, 0, 0, 0, 0, 0, 0, 0, 0, 0, 0, 0, 0, 0, 0, 0, 0, 0, 0, 0, 0, 0, 0, 0], [0, 0, 0, 0, 0, 0, 0, 0, 0, 0, 0, 0, 0, 0, 0, 0, 0, 0, 0, 0, 0, 0, 0, 0, 0, 0, 0, 0, 0, 0, 0, 0, 0, 0, 0, 0, 0, 0, 0, 0, 0, 0, 0, 0, 0, 0, 0, 0, 0, 0, 0, 0, 0, 0, 0, 0, 0, 0, 0, 0, 0, 0, 0, 0, 0, 0, 0, 0, 0, 0, 0, 0, 0, 0, 0, 0, 0, 0, 0, 0, 0, 0, 0, 0, 0, 0, 0, 0, 0, 0, 0, 0, 0, 0, 0, 0], [0, 0, 0, 0, 0, 0, 0, 0, 0, 0, 0, 0, 0, 0, 0, 0, 0, 0, 0, 0, 0, 0, 0, 0, 0, 0, 0, 0, 0, 0, 0, 0, 0, 0, 0, 0, 0, 0, 0, 0, 0, 0, 0, 0, 0, 0, 0, 0, 0, 0, 0, 0, 0, 0, 0, 0, 0, 0, 0, 0, 0, 0, 0, 0, 0, 0, 0, 0, 0, 0, 0, 0, 0, 0, 0, 0, 0, 0, 0, 0, 0, 0, 0, 0, 0, 0, 0, 0, 0, 0, 0, 0, 0, 0, 0, 0], [0, 0, 0, 0, 0, 0, 0, 0, 0, 0, 0, 0, 0, 0, 0, 0, 0, 0, 0, 0, 0, 0, 0, 0, 0, 0, 0, 0, 0, 0, 0, 0, 0, 0, 0, 0, 0, 0, 0, 0, 0, 0, 0, 0, 0, 0, 0, 0, 0, 0, 0, 0, 0, 0, 0, 0, 0, 0, 0, 0, 0, 0, 0, 0, 0, 0, 0, 0, 0, 0, 0, 0, 0, 0, 0, 0, 0, 0, 0, 0, 0, 0, 0, 0, 0, 0, 0, 0, 0, 0, 0, 0, 0, 0, 0, 0], [0, 0, 0, 0, 0, 0, 0, 0, 0, 0, 0, 0, 0, 0, 0, 0, 0, 0, 0, 0, 0, 0, 0, 0, 0, 0, 0, 0, 0, 0, 0, 0, 0, 0, 0, 0, 0, 0, 0, 0, 0, 0, 0, 0, 0, 0, 0, 0, 0, 0, 0, 0, 0, 0, 0, 0, 0, 0, 0, 0, 0, 0, 0, 0, 0, 0, 0, 0, 0, 0, 0, 0, 0, 0, 0, 0, 0, 0, 0, 0, 0, 0, 0, 0, 0, 0, 0, 0, 0, 0, 0, 0, 0, 0, 0, 0], [0, 0, 0, 0, 0, 0, 0, 0, 0, 0, 0, 0, 0, 0, 0, 0, 0, 0, 0, 0, 0, 0, 0, 0, 0, 0, 0, 0, 0, 0, 0, 0, 0, 0, 0, 0, 0, 0, 0, 0, 0, 0, 0, 0, 0, 0, 0, 0, 0, 0, 0, 0, 0, 0, 0, 0, 0, 0, 0, 0, 0, 0, 0, 0, 0, 0, 0, 0, 0, 0, 0, 0, 0, 0, 0, 0, 0, 0, 0, 0, 0, 0, 0, 0, 0, 0, 0, 0, 0, 0, 0, 0, 0, 0, 0, 0], [0, 0, 0, 0, 0, 0, 0, 0, 0, 0, 0, 0, 0, 0, 0, 0, 0, 0, 0, 0, 0, 0, 0, 0, 0, 0, 0, 0, 0, 0, 0, 0, 0, 0, 0, 0, 0, 0, 0, 0, 0, 0, 0, 0, 0, 0, 0, 0, 0, 0, 0, 0, 0, 0, 0, 0, 0, 0, 0, 0, 0, 0, 0, 0, 0, 0, 0, 0, 0, 0, 0, 0, 0, 0, 0, 0, 0, 0, 0, 0, 0, 0, 0, 0, 0, 0, 0, 0, 0, 0, 0, 0, 0, 0, 0, 0], [0, 0, 0, 0, 0, 0, 0, 0, 0, 0, 0, 0, 0, 0, 0, 0, 0, 0, 0, 0, 0, 0, 0, 0, 0, 0, 0, 0, 0, 0, 0, 0, 0, 0, 0, 0, 0, 0, 0, 0, 0, 0, 0, 0, 0, 0, 0, 0, 0, 0, 0, 0, 0, 0, 0, 0, 0, 0, 0, 0, 0, 0, 0, 0, 0, 0, 0, 0, 0, 0, 0, 0, 0, 0, 0, 0, 0, 0, 0, 0, 0, 0, 0, 0, 0, 0, 0, 0, 0, 0, 0, 0, 0, 0, 0, 0], [0, 0, 0, 0, 0, 0, 0, 0, 0, 0, 0, 0, 0, 0, 0, 0, 0, 0, 0, 0, 0, 0, 0, 0, 0, 0, 0, 0, 0, 0, 0, 0, 0, 0, 0, 0, 0, 0, 0, 0, 0, 0, 0, 0, 0, 0, 0, 0, 0, 0, 0, 0, 0, 0, 0, 0, 0, 0, 0, 0, 0, 0, 0, 0, 0, 0, 0, 0, 0, 0, 0, 0, 0, 0, 0, 0, 0, 0, 0, 0, 0, 0, 0, 0, 0, 0, 0, 0, 0, 0, 0, 0, 0, 0, 0, 0], [0, 0, 0, 0, 0, 0, 0, 0, 0, 0, 0, 0, 0, 0, 0, 0, 0, 0, 0, 0, 0, 0, 0, 0, 0, 0, 0, 0, 0, 0, 0, 0, 0, 0, 0, 0, 0, 0, 0, 0, 0, 0, 0, 0, 0, 0, 0, 0, 0, 0, 0, 0, 0, 0, 0, 0, 0, 0, 0, 0, 0, 0, 0, 0, 0, 0, 0, 0, 0, 0, 0, 0, 0, 0, 0, 0, 0, 0, 0, 0, 0, 0, 0, 0, 0, 0, 0, 0, 0, 0, 0, 0, 0, 0, 0, 0], [0, 0, 0, 0, 0, 0, 0, 0, 0, 0, 0, 0, 0, 0, 0, 0, 0, 0, 0, 0, 0, 0, 0, 0, 0, 0, 0, 0, 0, 0, 0, 0, 0, 0, 0, 0, 0, 0, 0, 0, 0, 0, 0, 0, 0, 0, 0, 0, 0, 0, 0, 0, 0, 0, 0, 0, 0, 0, 0, 0, 0, 0, 0, 0, 0, 0, 0, 0, 0, 0, 0, 0, 0, 0, 0, 0, 0, 0, 0, 0, 0, 0, 0, 0, 0, 0, 0, 0, 0, 0, 0, 0, 0, 0, 0, 0]]}